urlgen/__init__.py
urlgen-0.0.0.dist-info/METADATA
urlgen-0.0.0.dist-info/WHEEL
urlgen-0.0.0.dist-info/entry_points.txt
urlgen-0.0.0.dist-info/top_level.txt
urlgen-0.0.0.dist-info/RECORD
