Metadata-Version: 2.1
Name: urlgen
Version: 0.0.0
Summary: Get download URL from cloud storage service URL.
Home-page: UNKNOWN
Author: kazukazuprogram
Author-email: UNKNOWN
License: MIT
Platform: UNKNOWN
Classifier: Programming Language :: Python
Classifier: Programming Language :: Python :: 3.8
Classifier: License :: OSI Approved :: Python Software Foundation License
Classifier: Operating System :: MacOS :: MacOS X
Classifier: Operating System :: Microsoft :: Windows
Classifier: Operating System :: POSIX
Requires-Dist: bs4
Requires-Dist: requests
Requires-Dist: lxml
